{
  "applications": [
    {
      "id": 1778214735217,
      "name": "DB Save Test",
      "grade": "6",
      "parentName": "Parent DB",
      "email": "dbsave@test.com",
      "phone": "6666666666",
      "message": "save to db json",
      "submittedAt": "2026-05-08T04:32:15.213Z"
    },
    {
      "id": 1778214800963,
      "name": "kk",
      "grade": "jk",
      "parentName": "jkj",
      "email": "monikakommana@gmail.com",
      "phone": "000000000",
      "message": "nlo",
      "submittedAt": "2026-05-08T04:33:20.961Z"
    },
    {
      "id": 1778220621630,
      "name": "vemesh",
      "grade": "12",
      "parentName": "monika",
      "email": "monika@gmail.com",
      "phone": "1234567890",
      "message": "monika lives vemesh",
      "submittedAt": "2026-05-08T06:10:21.617Z"
    }
  ]
}